{"title":"redux-核心原理实现","uid":"d7d5d2dd3260dd6aeeea17300ba47f1e","slug":"redux/redux-核心原理实现","date":"2019-12-24T17:29:15.000Z","updated":"2021-04-13T07:58:54.188Z","comments":true,"path":"api/articles/redux/redux-核心原理实现.json","keywords":null,"cover":[],"content":"<h3 id=\"redux是什么\"><a href=\"#redux是什么\" class=\"headerlink\" title=\"redux是什么\"></a>redux是什么</h3><blockquote><span class=\"custom-blockquote-svg\"><svg width=\"24\" height=\"24\" viewBox=\"0 0 24 24\" fill=\"\" xmlns=\"http://www.w3.org/2000/svg\" data-reactroot=\"\">\n<path fill=\"\" d=\"M22 12C22 6.5 17.5 2 12 2C6.5 2 2 6.5 2 12C2 17.5 6.5 22 12 22C13.8 22 15.5 21.5 17 20.6L22 22L20.7 17C21.5 15.5 22 13.8 22 12Z\" undefined=\"1\"></path>\n<path fill=\"\" d=\"M15.97 11.5H16.04C17.12 11.5 18 12.38 18 13.47V13.53C18 14.62 17.12 15.5 16.03 15.5H15.96C14.88 15.5 14 14.62 14 13.53V13.46C14 12.38 14.88 11.5 15.97 11.5Z\" undefined=\"1\"></path>\n<path fill=\"\" d=\"M7.97 11.5H8.04C9.12 11.5 10 12.38 10 13.47V13.53C10 14.62 9.12 15.5 8.03 15.5H7.97C6.88 15.5 6 14.62 6 13.53V13.46C6 12.38 6.88 11.5 7.97 11.5Z\" undefined=\"1\"></path>\n<path stroke-linejoin=\"round\" stroke-linecap=\"round\" stroke-miterlimit=\"10\" stroke-width=\"2\" stroke=\"\" d=\"M17 8.5C15.23 8.97 14.07 10.84 14.01 13.27C14 13.33 14 13.4 14 13.47V13.5\"></path>\n<path stroke-linejoin=\"round\" stroke-linecap=\"round\" stroke-miterlimit=\"10\" stroke-width=\"2\" stroke=\"\" d=\"M9 8.5C7.23 8.97 6.07 10.84 6.01 13.27C6 13.33 6 13.4 6 13.47V13.5\"></path>\n<path stroke-linejoin=\"round\" stroke-linecap=\"round\" stroke-miterlimit=\"10\" stroke-width=\"2\" stroke=\"\" d=\"M15.97 11.5H16.04C17.12 11.5 18 12.38 18 13.47V13.53C18 14.62 17.12 15.5 16.03 15.5H15.96C14.88 15.5 14 14.62 14 13.53V13.46C14 12.38 14.88 11.5 15.97 11.5Z\"></path>\n<path stroke-linejoin=\"round\" stroke-linecap=\"round\" stroke-miterlimit=\"10\" stroke-width=\"2\" stroke=\"\" d=\"M7.97 11.5H8.04C9.12 11.5 10 12.38 10 13.47V13.53C10 14.62 9.12 15.5 8.03 15.5H7.97C6.88 15.5 6 14.62 6 13.53V13.46C6 12.38 6.88 11.5 7.97 11.5Z\"></path>\n</svg>\n</span><p>很多人认为redux必须要结合React使用，其实并不是的，Redux 是 JavaScript 状态容器，只要你的项目中使用到了状态，并且状态十分复杂，那么你就可以使用Redux管理你的项目状态，它可以使用在react中，也可以使用中在Vue中，当然也适用其他的框架。</p></blockquote>\n<span id=\"more\"></span>\n<h4 id=\"redux-工作原理\"><a href=\"#redux-工作原理\" class=\"headerlink\" title=\"redux 工作原理\"></a>redux 工作原理</h4><p><img src=\"http://wx2.sinaimg.cn/mw690/85eda507gy1fpkak6pk3pj20p10e1abo.jpg\" alt=\"enter image description here\"></p>\n<ol>\n<li>首先我们找到最上面的state</li>\n<li>在react中state决定了视图（ui），state的变化就会调用React的 render（）方法，从而改变视图</li>\n<li>用户通过一些事件（如点击按钮，移动鼠标）就会像reducer派发一个action</li>\n<li>reducer接收到action后就会去更新state</li>\n<li>store是包含了所有了state，可以把他看做所有状态的集合</li>\n</ol>\n<blockquote><span class=\"custom-blockquote-svg\"><svg width=\"24\" height=\"24\" viewBox=\"0 0 24 24\" fill=\"\" xmlns=\"http://www.w3.org/2000/svg\" data-reactroot=\"\">\n<path fill=\"\" d=\"M22 12C22 6.5 17.5 2 12 2C6.5 2 2 6.5 2 12C2 17.5 6.5 22 12 22C13.8 22 15.5 21.5 17 20.6L22 22L20.7 17C21.5 15.5 22 13.8 22 12Z\" undefined=\"1\"></path>\n<path fill=\"\" d=\"M15.97 11.5H16.04C17.12 11.5 18 12.38 18 13.47V13.53C18 14.62 17.12 15.5 16.03 15.5H15.96C14.88 15.5 14 14.62 14 13.53V13.46C14 12.38 14.88 11.5 15.97 11.5Z\" undefined=\"1\"></path>\n<path fill=\"\" d=\"M7.97 11.5H8.04C9.12 11.5 10 12.38 10 13.47V13.53C10 14.62 9.12 15.5 8.03 15.5H7.97C6.88 15.5 6 14.62 6 13.53V13.46C6 12.38 6.88 11.5 7.97 11.5Z\" undefined=\"1\"></path>\n<path stroke-linejoin=\"round\" stroke-linecap=\"round\" stroke-miterlimit=\"10\" stroke-width=\"2\" stroke=\"\" d=\"M17 8.5C15.23 8.97 14.07 10.84 14.01 13.27C14 13.33 14 13.4 14 13.47V13.5\"></path>\n<path stroke-linejoin=\"round\" stroke-linecap=\"round\" stroke-miterlimit=\"10\" stroke-width=\"2\" stroke=\"\" d=\"M9 8.5C7.23 8.97 6.07 10.84 6.01 13.27C6 13.33 6 13.4 6 13.47V13.5\"></path>\n<path stroke-linejoin=\"round\" stroke-linecap=\"round\" stroke-miterlimit=\"10\" stroke-width=\"2\" stroke=\"\" d=\"M15.97 11.5H16.04C17.12 11.5 18 12.38 18 13.47V13.53C18 14.62 17.12 15.5 16.03 15.5H15.96C14.88 15.5 14 14.62 14 13.53V13.46C14 12.38 14.88 11.5 15.97 11.5Z\"></path>\n<path stroke-linejoin=\"round\" stroke-linecap=\"round\" stroke-miterlimit=\"10\" stroke-width=\"2\" stroke=\"\" d=\"M7.97 11.5H8.04C9.12 11.5 10 12.38 10 13.47V13.53C10 14.62 9.12 15.5 8.03 15.5H7.97C6.88 15.5 6 14.62 6 13.53V13.46C6 12.38 6.88 11.5 7.97 11.5Z\"></path>\n</svg>\n</span><p><code>redux</code>的一些<code>api</code>及使用方法这里不再过多叙述  <strong>详情可以了解 redux 文档</strong>：<a href=\"https://www.redux.org.cn/\">redux 中文文档</a></p></blockquote>\n<h3 id=\"redux源码剖析\"><a href=\"#redux源码剖析\" class=\"headerlink\" title=\"redux源码剖析\"></a>redux源码剖析</h3><pre class=\"line-numbers language-none\"><code class=\"language-none\">&#x2F;&#x2F; redux : 精简源码，只写了核心原理\n\nexport function createStore(reducer) &#123;\n    &#x2F;&#x2F; 创建store状态\n    let state;\n    &#x2F;&#x2F; store事件池\n    let listeners &#x3D; [];\n\n    &#x2F;&#x2F; 获取state状态信息\n    function getState() &#123;\n        &#x2F;&#x2F; redux不允许直接更改state，但是源码中又没有做相应的处理\n        &#x2F;&#x2F; 这里用JSON做一个简单的深克隆处理\n        return JSON.parse(JSON.stringify(state));\n    &#125;\n\n    &#x2F;&#x2F; 派发提交\n    function dispatch(action) &#123;\n        state &#x3D; reducer(state, action);\n\n        &#x2F;&#x2F; 每次dispatch以后，都要发布一下事件池\n        listeners.forEach(item &#x3D;&gt; &#123;\n            if (typeof item &#x3D;&#x3D;&#x3D; &quot;function&quot;) item();\n        &#125;);\n    &#125;\n\n    &#x2F;&#x2F; 订阅\n    function subscribe(func) &#123;\n        &#x2F;&#x2F; 在redux源码中并没有做事件池去重； 个人觉得要做一下去重\n        if (!listeners.includes(func)) listeners.push(func);\n\n        &#x2F;&#x2F; subscribe(): 会返回一个函数，用来从事件池中移除当前事件 (取消订阅)\n        return function unSubscribe() &#123;\n            &#x2F;&#x2F; 为防止数组塌陷问题，这里用filter替代splice移除数组项\n            listeners &#x3D; listeners.filter(item &#x3D;&gt; item !&#x3D;&#x3D; func);\n        &#125;\n    &#125;\n\n    &#x2F;&#x2F; 初始化state，创建store时默认派发一次\n    dispatch(&#123;\n        &#x2F;&#x2F; 初始派发的type值一定不要和项目中的type值有重复的；这里redux源码做了一个随机数截取处理转字符串所生成的一个尽可能不重复的type初始值\n        type: &quot;@@redux&#x2F;INIT&quot; + Date.now()  &#x2F;&#x2F; 简单操作一下，其实也可以不传type\n    &#125;);\n\n    return &#123;\n        getState,\n        dispatch,\n        subscribe\n    &#125;\n&#125;\n\n&#x2F;&#x2F; combineReducers: 合并reducer\nexport function combineReducers(reducers) &#123;\n    &#x2F;&#x2F; 创建store初始化state。默认 &#x3D; &#123;&#125;\n    return function (state &#x3D; &#123;&#125;, action) &#123;\n        let combineState &#x3D; &#123;&#125;;\n        for (let key in reducers) &#123;\n            if (!reducers.hasOwnProperty(key)) break;\n            combineState[key] &#x3D; reducers[key](state[key], action);\n        &#125;\n        return combineState;\n        &#x2F;&#x2F; 最终state : &#123; module1: &#123;..&#125;, module2: &#123;..&#125;, .....&#125;\n        &#x2F;&#x2F; 初始化创建之后，以后的每一次执行dispatch，都会让每一个组件模块下的reducer执行，且会把state中对应组件名的对应数据传入reducer   &#x3D;&#x3D;&gt;  reducer(state.module, action)\n    &#125;\n&#125;\n<span aria-hidden=\"true\" class=\"line-numbers-rows\"><span></span><span></span><span></span><span></span><span></span><span></span><span></span><span></span><span></span><span></span><span></span><span></span><span></span><span></span><span></span><span></span><span></span><span></span><span></span><span></span><span></span><span></span><span></span><span></span><span></span><span></span><span></span><span></span><span></span><span></span><span></span><span></span><span></span><span></span><span></span><span></span><span></span><span></span><span></span><span></span><span></span><span></span><span></span><span></span><span></span><span></span><span></span><span></span><span></span><span></span><span></span><span></span><span></span><span></span><span></span><span></span><span></span><span></span><span></span><span></span><span></span><span></span><span></span><span></span></span></code></pre>\n<p>这里只精简写了一下<code>redux</code>核心工作原理, 还有一些<code>bindActionCreators</code>、<code>applyMiddleware</code>、<code>compose</code>…..其他的<code>api</code>后续会再详情探究一下</p>\n<p>~~嗝了</p>\n","text":"redux是什么 很多人认为redux必须要结合React使用，其实并不是的，Redux 是 JavaScript 状态容器，只要你的项目中使用到了状态，并且状态十分复杂，那么你就可以使用Redux管理你的项目状态，它可以使用在react中，也可以使用中在Vue中，当然也适用其他...","link":"","photos":[],"count_time":{"symbolsCount":"2.7k","symbolsTime":"2 mins."},"categories":[],"tags":[{"name":"redux","slug":"redux","count":3,"path":"api/tags/redux.json"}],"toc":"<ol class=\"toc\"><li class=\"toc-item toc-level-3\"><a class=\"toc-link\" href=\"#redux%E6%98%AF%E4%BB%80%E4%B9%88\"><span class=\"toc-text\">redux是什么</span></a><ol class=\"toc-child\"><li class=\"toc-item toc-level-4\"><a class=\"toc-link\" href=\"#redux-%E5%B7%A5%E4%BD%9C%E5%8E%9F%E7%90%86\"><span class=\"toc-text\">redux 工作原理</span></a></li></ol></li><li class=\"toc-item toc-level-3\"><a class=\"toc-link\" href=\"#redux%E6%BA%90%E7%A0%81%E5%89%96%E6%9E%90\"><span class=\"toc-text\">redux源码剖析</span></a></li></ol>","author":{"name":"zhangone","slug":"blog-author","avatar":"https://cdn.jsdelivr.net/gh/zhangone233/photo_bed@aurora/img/about/avatar.jpeg","link":"https://zhangone233.github.io/zhangone233/","description":"博客简介","socials":{"github":"https://github.com/zhangone233","twitter":"","stackoverflow":"","wechat":"","qq":"","weibo":"","zhihu":"","csdn":"","juejin":"","customs":{}}},"mapped":true,"prev_post":{"title":"react-redux原理实现","uid":"b2c6522645fcbca2b7cc17045d2aca02","slug":"redux/react-redux原理实现","date":"2020-01-11T17:30:14.000Z","updated":"2021-04-13T07:58:54.186Z","comments":true,"path":"api/articles/redux/react-redux原理实现.json","keywords":null,"cover":[],"text":"先简单了解一下 react-redux 一、组件分类React-Redux 将所有组件分成两大类：UI 组件（presentational component）和容器组件（container component）。 UI 组件： 只负责 UI 的呈现，不带有任何业务逻辑 没有状态...","link":"","photos":[],"count_time":{"symbolsCount":"6.9k","symbolsTime":"6 mins."},"categories":[],"tags":[{"name":"redux","slug":"redux","count":3,"path":"api/tags/redux.json"}],"author":{"name":"zhangone","slug":"blog-author","avatar":"https://cdn.jsdelivr.net/gh/zhangone233/photo_bed@aurora/img/about/avatar.jpeg","link":"https://zhangone233.github.io/zhangone233/","description":"博客简介","socials":{"github":"https://github.com/zhangone233","twitter":"","stackoverflow":"","wechat":"","qq":"","weibo":"","zhihu":"","csdn":"","juejin":"","customs":{}}}},"next_post":{"title":"VUE-component","uid":"0e59b960ff94f4b3c8757aabc03ddab4","slug":"Vue/VUE-component","date":"2019-11-11T04:22:59.000Z","updated":"2021-04-13T07:58:54.181Z","comments":true,"path":"api/articles/Vue/VUE-component.json","keywords":null,"cover":[],"text":"VUE中的组件组件的特点是： 每个组件就是一个自定义标签 可复用 方便维护 方便拆分 每个组件作用域隔离（互不干扰） 有完整的生命周期 有自己的响应式数据和各种方法（事件） … 组件的组织 通常一个应用会以一棵嵌套的组件树的形式来组织： ####1. 全局组件 &amp; 组件的...","link":"","photos":[],"count_time":{"symbolsCount":"3.2k","symbolsTime":"3 mins."},"categories":[],"tags":[{"name":"Vue","slug":"Vue","count":3,"path":"api/tags/Vue.json"}],"author":{"name":"zhangone","slug":"blog-author","avatar":"https://cdn.jsdelivr.net/gh/zhangone233/photo_bed@aurora/img/about/avatar.jpeg","link":"https://zhangone233.github.io/zhangone233/","description":"博客简介","socials":{"github":"https://github.com/zhangone233","twitter":"","stackoverflow":"","wechat":"","qq":"","weibo":"","zhihu":"","csdn":"","juejin":"","customs":{}}}}}